{
  "name": "RentEverything Local Env",
  "values": [
    {
      "key": "baseUrl",
      "value": "http://localhost:3000",
      "type": "default",
      "enabled": true
    },
    {
      "key": "accessToken",
      "value": "",
      "type": "default",
      "enabled": true
    },
    {
      "key": "refreshToken",
      "value": "",
      "type": "default",
      "enabled": true
    },
    {
      "key": "userId",
      "value": "",
      "type": "default",
      "enabled": true
    },
    {
      "key": "categoryId",
      "value": "",
      "type": "default",
      "enabled": true
    },
    {
      "key": "listingId",
      "value": "",
      "type": "default",
      "enabled": true
    },
    {
      "key": "bookingId",
      "value": "",
      "type": "default",
      "enabled": true
    },
    {
      "key": "reviewId",
      "value": "",
      "type": "default",
      "enabled": true
    },
    {
      "key": "conversationId",
      "value": "",
      "type": "default",
      "enabled": true
    }
  ]
}